.gitignore
COPYING
README
setup.cfg
setup.py
examples/calc.py
examples/fib.py
examples/hello.py
examples/japp.py
examples/jquery-2.1.1.js
examples/sse-time.html
examples/sse-time.py
examples/sse-top.html
examples/sse-top.py
tawf/__init__.py
tawf/api.py
tawf/handler.py
tawf.egg-info/PKG-INFO
tawf.egg-info/SOURCES.txt
tawf.egg-info/dependency_links.txt
tawf.egg-info/requires.txt
tawf.egg-info/top_level.txt
tawf/tests/__init__.py
tawf/tests/test_api.py
tawf/tests/test_handler.py