Metadata-Version: 1.1
Name: tawf
Version: 0.3.0
Summary: tawf - functions and coroutines to create RESTful servers
Home-page: https://bitbucket.org/wrobell/tawf
Author: Artur Wroblewski
Author-email: wrobell@pld-linux.org
License: GPL
Platform: UNKNOWN
Classifier: License :: OSI Approved :: GNU General Public License v3 or later (GPLv3+)
Classifier: Programming Language :: Python :: 3
Classifier: Development Status :: 2 - Pre-Alpha
